AUTHORS.rst
CONTRIBUTING.rst
HISTORY.rst
LICENSE
MANIFEST.in
README.rst
setup.cfg
setup.py
docs/Makefile
docs/authors.rst
docs/conf.py
docs/contributing.rst
docs/history.rst
docs/index.rst
docs/installation.rst
docs/make.bat
docs/modules.rst
docs/readme.rst
docs/trapecio_compuesto.rst
docs/usage.rst
docs/_build/html/_static/ajax-loader.gif
docs/_build/html/_static/comment-bright.png
docs/_build/html/_static/comment-close.png
docs/_build/html/_static/comment.png
docs/_build/html/_static/down-pressed.png
docs/_build/html/_static/down.png
docs/_build/html/_static/file.png
docs/_build/html/_static/minus.png
docs/_build/html/_static/plus.png
docs/_build/html/_static/up-pressed.png
docs/_build/html/_static/up.png
tests/test_trapecio_compuesto.py
trapecio_compuesto/__init__.py
trapecio_compuesto/cli.py
trapecio_compuesto/trapecio_compuesto.py
trapecio_compuesto.egg-info/PKG-INFO
trapecio_compuesto.egg-info/SOURCES.txt
trapecio_compuesto.egg-info/dependency_links.txt
trapecio_compuesto.egg-info/entry_points.txt
trapecio_compuesto.egg-info/not-zip-safe
trapecio_compuesto.egg-info/requires.txt
trapecio_compuesto.egg-info/top_level.txt