Metadata-Version: 1.1
Name: trapecio-compuesto
Version: 0.1.0
Summary: trapecio-compuesto metodo numerico
Home-page: https://github.com/estebanx64/trapecio_compuesto
Author: Esteban Maya
Author-email: emayacadavid9@gmail.com
License: MIT license
Keywords: trapecio_compuesto
Platform: UNKNOWN
Classifier: Development Status :: 2 - Pre-Alpha
Classifier: Intended Audience :: Developers
Classifier: License :: OSI Approved :: MIT License
Classifier: Natural Language :: English
Classifier: Programming Language :: Python :: 2
Classifier: Programming Language :: Python :: 2.7
Classifier: Programming Language :: Python :: 3
Classifier: Programming Language :: Python :: 3.4
Classifier: Programming Language :: Python :: 3.5
Classifier: Programming Language :: Python :: 3.6
